bioliterature/__init__.py
bioliterature/__main__.py
bioliterature/analyze.py
bioliterature/annotate.py
bioliterature/cli.py
bioliterature/py.typed
bioliterature/retrieve.py
bioliterature/version.py
bioliterature-0.0.2.dist-info/licenses/LICENSE
bioliterature-0.0.2.dist-info/WHEEL
bioliterature-0.0.2.dist-info/entry_points.txt
bioliterature-0.0.2.dist-info/METADATA
bioliterature-0.0.2.dist-info/RECORD
