Metadata-Version: 2.4
Name: bioliterature
Version: 0.0.2
Summary: Access and analyze biomedical literature
Keywords: snekpack,cookiecutter
Author: Charles Tapley Hoyt
Author-email: Charles Tapley Hoyt <cthoyt@gmail.com>
License-File: LICENSE
Classifier: Development Status :: 1 - Planning
Classifier: Environment :: Console
Classifier: Intended Audience :: Developers
Classifier: License :: OSI Approved :: MIT License
Classifier: Operating System :: OS Independent
Classifier: Framework :: Pytest
Classifier: Framework :: tox
Classifier: Framework :: Sphinx
Classifier: Natural Language :: English
Classifier: Programming Language :: Python
Classifier: Programming Language :: Python :: 3.10
Classifier: Programming Language :: Python :: 3.11
Classifier: Programming Language :: Python :: 3.12
Classifier: Programming Language :: Python :: 3.13
Classifier: Programming Language :: Python :: 3 :: Only
Classifier: Typing :: Typed
Requires-Dist: curies
Requires-Dist: ssslm[gilda-slim]>=0.0.11
Requires-Dist: pydantic
Requires-Dist: tqdm
Requires-Dist: pandas
Requires-Dist: more-itertools
Requires-Dist: pubmed-downloader>=0.0.9
Requires-Dist: sphinx>=8 ; extra == 'docs'
Requires-Dist: sphinx-rtd-theme>=3.0 ; extra == 'docs'
Requires-Dist: sphinx-click ; extra == 'docs'
Requires-Dist: sphinx-automodapi ; extra == 'docs'
Requires-Dist: indra ; extra == 'indra'
Requires-Dist: pytest ; extra == 'tests'
Requires-Dist: coverage[toml] ; extra == 'tests'
Requires-Dist: biolexica>=0.1.0 ; extra == 'tests'
Maintainer: Charles Tapley Hoyt
Maintainer-email: Charles Tapley Hoyt <cthoyt@gmail.com>
Requires-Python: >=3.10
Project-URL: Bug Tracker, https://github.com/cthoyt/bioliterature/issues
Project-URL: Documentation, https://bioliterature.readthedocs.io
Project-URL: Funding, https://github.com/sponsors/cthoyt
Project-URL: Homepage, https://github.com/cthoyt/bioliterature
Project-URL: Repository, https://github.com/cthoyt/bioliterature.git
Provides-Extra: docs
Provides-Extra: indra
Provides-Extra: tests
